    {
  "winMessage": "Whoa...! How are you so unbelievably good?!?",
  "people": {
    "trump": {
      "x": 630,
      "y": 470,
      "facing": "Left"
    },
    "woman": {
      "x": 550,
      "y": 400,
      "facing": "Left"
    },
    "man2": {
      "x": 320,
      "y": 410,
      "facing": "Right"
    },
    "woman2": {
      "x": 240,
      "y": 460,
      "facing": "Right"
    }
  },
  "scenes": [
    {
      "dur": 1.5,
      "type": "Wait",
      "sprite": "trump",
      "x": null,
      "y": null,
      "anim": "walk",
      "locker": false,
      "isGap": false
    },
    {
      "dur": 3,
      "type": "AnimScene",
      "sprite": "trump",
      "x": 590,
      "y": 460,
      "anim": "walk",
      "locker": false,
      "isGap": false,
      "facing": "Left"
    },
    {
      "dur": 3,
      "type": "AnimScene",
      "sprite": "woman",
      "x": 530,
      "y": 390,
      "anim": "walk",
      "locker": false,
      "isGap": false,
      "facing": "Left"
    },
    {
      "dur": 3,
      "type": "AnimScene",
      "sprite": "man2",
      "x": 400,
      "y": 400,
      "anim": "walk",
      "locker": false,
      "isGap": false,
      "facing": "Right"
    },
    {
      "dur": 3,
      "type": "AnimScene",
      "sprite": "woman2",
      "x": 330,
      "y": 450,
      "anim": "walk",
      "locker": true,
      "isGap": false,
      "facing": "Right"
    },
    {
      "dur": 0,
      "type": "AnimScene",
      "sprite": "trump",
      "x": 590,
      "y": 460,
      "anim": "stop",
      "locker": false,
      "isGap": false,
      "facing": "Left"
    },
    {
      "dur": 0,
      "type": "AnimScene",
      "sprite": "woman",
      "x": 530,
      "y": 390,
      "anim": "stop",
      "locker": false,
      "isGap": false,
      "facing": "Left"
    },
    {
      "dur": 0,
      "type": "AnimScene",
      "sprite": "man2",
      "x": 400,
      "y": 400,
      "anim": "stop",
      "locker": false,
      "isGap": false,
      "facing": "Right"
    },
    {
      "dur": 0.5,
      "type": "AnimScene",
      "sprite": "woman2",
      "x": 330,
      "y": 450,
      "anim": "stop",
      "locker": true,
      "isGap": false,
      "facing": "Right"
    },
    {
      "dur": 0,
      "type": "AnimScene",
      "sprite": "woman",
      "x": 530,
      "y": 390,
      "anim": "hand",
      "locker": false,
      "isGap": false,
      "facing": "Left"
    },
    {
      "dur": 1,
      "type": "AnimScene",
      "sprite": "man2",
      "x": 400,
      "y": 400,
      "anim": "hand",
      "locker": true,
      "isGap": false,
      "facing": "Right"
    },
    {
      "dur": 0,
      "type": "AnimScene",
      "sprite": "woman2",
      "x": 320,
      "y": 450,
      "anim": "uptight",
      "locker": false,
      "isGap": false,
      "facing": "Right"
    },
    {
      "dur": 1.2,
      "type": "AnimScene",
      "sprite": "trump",
      "x": 540,
      "y": 460,
      "anim": "walk",
      "locker": false,
      "isGap": false,
      "facing": "Left"
    },
    {
      "dur": 1.2,
      "type": "AvoidTask",
      "x": 700,
      "y": 240,
      "locker": true
    },
    {
      "dur": 1,
      "type": "AnimScene",
      "sprite": "trump",
      "x": 450,
      "y": 460,
      "anim": "hand",
      "locker": false,
      "isGap": false,
      "facing": "Left"
    },
    {
      "dur": 1,
      "type": "AvoidTask",
      "x": 600,
      "y": 200,
      "locker": true
    },
    {
      "dur": 1.5,
      "type": "AnimScene",
      "sprite": "trump",
      "x": 300,
      "y": 460,
      "anim": "walk",
      "locker": false,
      "isGap": false,
      "facing": "Left"
    },
    {
      "dur": 1,
      "type": "AnimScene",
      "sprite": "man2",
      "x": 400,
      "y": 400,
      "anim": "stop",
      "locker": true,
      "isGap": false,
      "facing": "Right"
    },
    {
      "dur": 1.5,
      "type": "AnimScene",
      "sprite": "woman2",
      "x": 420,
      "y": 430,
      "anim": "hand",
      "locker": false,
      "isGap": false,
      "facing": "Right"
    },
    {
      "dur": 1.5,
      "type": "AnimScene",
      "sprite": "woman",
      "x": 530,
      "y": 410,
      "anim": "hand",
      "locker": true,
      "isGap": false,
      "facing": "Left"
    },
    {
      "dur": 1.5,
      "type": "AnimScene",
      "sprite": "trump",
      "x": 300,
      "y": 460,
      "anim": "shocked",
      "locker": false,
      "isGap": false,
      "facing": "Right"
    },
    {
      "dur": 1,
      "type": "Wait",
      "sprite": "trump",
      "x": 0,
      "y": 0,
      "anim": "shocked",
      "locker": false,
      "isGap": true,
      "facing": "Right"
    },
    {
      "dur": 0,
      "type": "AnimScene",
      "sprite": "woman",
      "x": 530,
      "y": 410,
      "anim": "stop",
      "locker": false,
      "isGap": false,
      "facing": "Left"
    },
    {
      "dur": 1.5,
      "type": "AnimScene",
      "sprite": "woman2",
      "x": 580,
      "y": 450,
      "anim": "walk",
      "locker": true,
      "isGap": false,
      "facing": "Right"
    },
    {
      "dur": 0,
      "type": "AnimScene",
      "sprite": "woman2",
      "x": 580,
      "y": 450,
      "anim": "stop",
      "locker": false,
      "isGap": false,
      "facing": "Left"
    },
    {
      "dur": 0,
      "type": "AnimScene",
      "sprite": "trump",
      "x": 300,
      "y": 460,
      "anim": "stop",
      "locker": true,
      "isGap": false,
      "facing": "Right"
    },
    {
      "dur": 2.5,
      "type": "Wait",
      "sprite": "trump",
      "x": 40,
      "y": null,
      "anim": "stop",
      "locker": true,
      "isGap": true,
      "facing": ""
    },
    {
      "dur": 0.4,
      "type": "AnimScene",
      "sprite": "trump",
      "x": 310,
      "y": 460,
      "anim": "dance",
      "locker": true,
      "isGap": false,
      "facing": "Right"
    },
    {
      "dur": 2.5,
      "type": "AnimScene",
      "sprite": "trump",
      "x": 350,
      "y": 460,
      "anim": "stop",
      "locker": true,
      "isGap": false,
      "facing": "Right"
    },
    {
      "dur": 0.6,
      "type": "Wait",
      "sprite": "trump",
      "x": 10,
      "y": null,
      "anim": "dance",
      "locker": true,
      "isGap": true,
      "facing": "Left"
    },
    {
      "dur": 0.4,
      "type": "AnimScene",
      "sprite": "trump",
      "x": 360,
      "y": 460,
      "anim": "dance",
      "locker": true,
      "isGap": false,
      "facing": "Left"
    },
    {
      "dur": 2.5,
      "type": "AnimScene",
      "sprite": "trump",
      "x": 400,
      "y": 460,
      "anim": "stop",
      "locker": true,
      "isGap": false,
      "facing": "Right"
    },
    {
      "dur": 0.6,
      "type": "Wait",
      "sprite": "trump",
      "x": 10,
      "y": null,
      "anim": "dance",
      "locker": true,
      "isGap": true,
      "facing": "Left"
    },
    {
      "dur": 0.4,
      "type": "AnimScene",
      "sprite": "trump",
      "x": 450,
      "y": 460,
      "anim": "dance",
      "locker": true,
      "isGap": false,
      "facing": "Right"
    },
    {
      "dur": 3,
      "type": "AnimScene",
      "sprite": "trump",
      "x": 520,
      "y": 460,
      "anim": "hand",
      "locker": false,
      "isGap": false,
      "facing": "Right"
    },
    {
      "dur": 3,
      "type": "AnimScene",
      "sprite": "woman2",
      "x": 600,
      "y": 450,
      "anim": "walk",
      "locker": false,
      "isGap": false,
      "facing": "Left"
    },
    {
      "dur": 1.1,
      "type": "AvoidTask",
      "x": 480,
      "y": 260,
      "locker": true
    },
    {
      "dur": 1,
      "type": "AvoidTask",
      "x": 480,
      "y": 260,
      "locker": true
    },
    {
      "dur": 0.9,
      "type": "AvoidTask",
      "x": 480,
      "y": 260,
      "locker": true
    },
    {
      "dur": 0.9,
      "type": "Win",
      "sprite": "trump",
      "x": 480,
      "y": 260,
      "anim": "dance",
      "locker": true,
      "isGap": true,
      "facing": ""
    },
    {
      "dur": 2,
      "type": "AnimScene",
      "sprite": "woman2",
      "x": -100,
      "y": 450,
      "anim": "jump",
      "locker": false,
      "isGap": false,
      "facing": "Left"
    },
    {
      "dur": 1,
      "type": "AnimScene",
      "sprite": "trump",
      "x": 570,
      "y": 460,
      "anim": "shocked",
      "locker": true,
      "isGap": false,
      "facing": "Right"
    },
    {
      "dur": 1.2,
      "type": "AnimScene",
      "sprite": "trump",
      "x": 620,
      "y": 460,
      "anim": "walk",
      "locker": true,
      "isGap": false,
      "facing": "Left"
    },
    {
      "dur": 0.5,
      "type": "AnimScene",
      "sprite": "trump",
      "x": 620,
      "y": 460,
      "anim": "stop",
      "locker": false,
      "isGap": false,
      "facing": "Left"
    }
  ],
  "name": "A Polish Greeting"
}
